egta/__init__.py
egta/__main__.py
egta/asyncgame.py
egta/bootstrap.py
egta/canonsched.py
egta/countsched.py
egta/eosched.py
egta/gamesched.py
egta/innerloop.py
egta/profsched.py
egta/savesched.py
egta/schedgame.py
egta/simsched.py
egta/trace.py
egta/utils.py
egta/zipsched.py
egta/script/__init__.py
egta/script/bootstrap.py
egta/script/brute.py
egta/script/eosched.py
egta/script/gamesched.py
egta/script/innerloop.py
egta/script/schedspec.py
egta/script/simsched.py
egta/script/trace.py
egta/script/utils.py
egta/script/zipsched.py
egta-0.2.2.dist-info/LICENSE
egta-0.2.2.dist-info/METADATA
egta-0.2.2.dist-info/WHEEL
egta-0.2.2.dist-info/entry_points.txt
egta-0.2.2.dist-info/top_level.txt
egta-0.2.2.dist-info/RECORD
