Metadata-Version: 2.1
Name: egta
Version: 0.2.2
Summary: Scripts to perform EGTA
Home-page: https://github.com/egtaonline/quiesce.git
Author: Strategic Reasoning Group
Author-email: strategic.reasoning.group@umich.edu
License: Apache 2.0
Platform: UNKNOWN
Requires-Dist: gameanalysis (~=8.1.0)
Requires-Dist: egtaonlineapi (==0.8.7)
Requires-Dist: numpy (~=1.18.0)
Provides-Extra: dev
Requires-Dist: black (~=20.8b1) ; extra == 'dev'
Requires-Dist: ipython (~=7.19) ; extra == 'dev'
Requires-Dist: pylint (~=2.6) ; extra == 'dev'
Requires-Dist: pytest-asyncio (~=0.14) ; extra == 'dev'
Requires-Dist: pytest-cov (~=2.10) ; extra == 'dev'
Requires-Dist: pytest-env (~=0.6) ; extra == 'dev'
Requires-Dist: pytest-timeout (~=1.4) ; extra == 'dev'
Requires-Dist: pytest-xdist (~=2.1) ; extra == 'dev'
Requires-Dist: pytest (~=6.1) ; extra == 'dev'
Requires-Dist: sphinx (~=1.7) ; extra == 'dev'
Requires-Dist: timeout-decorator (~=0.4) ; extra == 'dev'
Requires-Dist: twine (~=3.2) ; extra == 'dev'
Requires-Dist: wheel (~=0.35) ; extra == 'dev'
